src/lucas/__init__.py
src/lucas/main.py
pepitoww-0.0.1.dist-info/METADATA
pepitoww-0.0.1.dist-info/WHEEL
pepitoww-0.0.1.dist-info/licenses/LICENSE
pepitoww-0.0.1.dist-info/RECORD
